{
  "id": "20260402_075714_clip_10_percentiles",
  "experiment_number": 17,
  "name": "clip_10_percentiles",
  "block": "D",
  "timestamp": "2026-04-02T08:07:26+00:00",
  "mode": "full",
  "status": "crashed",
  "duration_seconds": 611,
  "cost_usd": 0,
  "seed": 1337,
  "code_hash": "7ee7d0832ca1d234a22bd8140955b4fe",
  "previous_best_bpb": A,
  "metrics": {
    "val_bpb": 5.17252588,
    "val_loss": 8.73359329,
    "final_train_loss": 2.7572,
    "artifact_bytes": 9518229,
    "total_params": 26993756,
    "total_steps": 465,
    "step_avg_ms": 646.47,
    "delta_vs_best": null
  },
  "config": {
    "model_dim": null,
    "num_layers": null,
    "seq_len": 2048,
    "matrix_lr": 0.025,
    "weight_decay": null,
    "batch_tokens": 786432
  },
  "loss_curve": "",
  "diff_file": "experiments/diff_20260402_075714_clip_10_percentiles.patch",
  "diff_summary": "diff --git a/train_gpt.py b/train_gpt.py\nindex 8a3d7ff..fa8fd23 100644\n--- a/train_gpt.py\n+++ b/train_gpt.py\n@@ -886,7 +886,7 @@ def quantize_int6_per_row(t: Tensor, clip_range: int = 31) -> tuple[Tensor, Tens\n     t32 = t.float()\n     if t32.ndim == 2:\n         best_q, best_s, best_err = None, None, float('inf')\n-        for pct in [0.9990, 0.9995, 0.9999, 0.99999, 1.0]:\n+        for pct in [0.9970, 0.9980, 0.9985, 0.9990, 0.9995, 0.9997, 0.9999, 0.99995, 0.99999, 1.0]:\n             if pct < 1.0:\n                 row_clip = torch.quantile(t32.abs(), pct, dim=1)\n             else:\n",
  "log_file": "logs/exp_20260402_075714_clip_10_percentiles.log"
}
